redenlab_extract/__init__.py
redenlab_extract/api.py
redenlab_extract/auth.py
redenlab_extract/client.py
redenlab_extract/config.py
redenlab_extract/exceptions.py
redenlab_extract/payload.py
redenlab_extract/polling.py
redenlab_extract/upload.py
redenlab_extract/utils.py
redenlab_extract-0.4.0.dist-info/METADATA
redenlab_extract-0.4.0.dist-info/WHEEL
redenlab_extract-0.4.0.dist-info/licenses/LICENSE
redenlab_extract-0.4.0.dist-info/RECORD
