Metadata-Version: 2.4
Name: redenlab-extract
Version: 0.4.0
Summary: Python SDK for RedenLab ML inference service
Project-URL: Homepage, https://redenlab.com
Project-URL: Repository, https://git-codecommit.us-west-2.amazonaws.com/v1/repos/redenlab-extract
Author-email: RedenLab <contact@redenlab.com>
License: MIT
License-File: LICENSE
Keywords: audio,extraction,inference,ml,sagemaker,speech
Classifier: Development Status :: 3 - Alpha
Classifier: Intended Audience :: Developers
Classifier: License :: OSI Approved :: MIT License
Classifier: Programming Language :: Python :: 3
Classifier: Programming Language :: Python :: 3.10
Classifier: Programming Language :: Python :: 3.11
Classifier: Programming Language :: Python :: 3.12
Classifier: Topic :: Scientific/Engineering :: Artificial Intelligence
Requires-Python: >=3.10
Requires-Dist: numpy>=1.20.0
Requires-Dist: pyyaml>=6.0
Requires-Dist: requests>=2.31.0
Requires-Dist: soundfile>=0.12.0
Requires-Dist: tenacity>=8.2.0
Provides-Extra: dev
Requires-Dist: black>=23.7.0; extra == 'dev'
Requires-Dist: mypy>=1.5.0; extra == 'dev'
Requires-Dist: pytest-cov>=4.1.0; extra == 'dev'
Requires-Dist: pytest-mock>=3.11.0; extra == 'dev'
Requires-Dist: pytest>=7.4.0; extra == 'dev'
Requires-Dist: responses>=0.23.0; extra == 'dev'
Requires-Dist: ruff>=0.0.285; extra == 'dev'
Requires-Dist: types-pyyaml>=6.0.0; extra == 'dev'
Requires-Dist: types-requests>=2.31.0; extra == 'dev'
Provides-Extra: test
Requires-Dist: pytest-cov>=4.1.0; extra == 'test'
Requires-Dist: pytest-mock>=3.11.0; extra == 'test'
Requires-Dist: pytest>=7.4.0; extra == 'test'
Requires-Dist: responses>=0.23.0; extra == 'test'
